potatoscript/potatoConfig.py
python/CodeTemplate.py
python/pyTemplate.py
python/pypiTemplate.py
python/pythonTemplate.py
python/xTemplate.py
xTemplate-1.4.2.dist-info/METADATA
xTemplate-1.4.2.dist-info/WHEEL
xTemplate-1.4.2.dist-info/top_level.txt
xTemplate-1.4.2.dist-info/RECORD
