Metadata-Version: 2.1
Name: xTemplate
Version: 1.4.2
Summary: A simple Template for create python project
Author: ks lim
Author-email: kianseng.lim@sony.com
